cmdfor/__init__.py
cmdfor/_version.py
cmdfor/cli.py
cmdfor/cmdfor.py
cmdfor-0.1.5.dist-info/DESCRIPTION.rst
cmdfor-0.1.5.dist-info/METADATA
cmdfor-0.1.5.dist-info/RECORD
cmdfor-0.1.5.dist-info/WHEEL
cmdfor-0.1.5.dist-info/entry_points.txt
cmdfor-0.1.5.dist-info/metadata.json
cmdfor-0.1.5.dist-info/top_level.txt
