Metadata-Version: 2.0
Name: cmdfor
Version: 0.1.5
Summary: Run cmd for every line of input
Home-page: https://github.com/jwgalley/cmdfor
Author: Jesse Galley
Author-email: jesse@jessegalley.net
License: MIT
Platform: UNKNOWN
Classifier: Development Status :: 2 - Pre-Alpha
Classifier: Intended Audience :: Developers
Classifier: License :: OSI Approved :: MIT License
Classifier: Natural Language :: English
Classifier: Programming Language :: Python :: 2.7
Classifier: Programming Language :: Python :: 3
Classifier: Programming Language :: Python :: 3.3
Classifier: Programming Language :: Python :: 3.4
Classifier: Programming Language :: Python :: 3.5
Requires-Dist: click
